dashcli/__init__.py
dashcli/dashcli.py
relcli-2.1.dist-info/METADATA
relcli-2.1.dist-info/WHEEL
relcli-2.1.dist-info/entry_points.txt
relcli-2.1.dist-info/top_level.txt
relcli-2.1.dist-info/RECORD
