Metadata-Version: 2.1
Name: relcli
Version: 2.1
Summary: A custom CLI tool for Relatient users to manage the AWS ECS clusters and connecting to PostgreSQL databases
Home-page: https://github.com/isiddharthrao
Author: Siddharth Rao
Author-email: isiddharthrao@gmail.com
Classifier: Programming Language :: Python :: 3
Classifier: License :: OSI Approved :: MIT License
Classifier: Operating System :: OS Independent
Requires-Python: >=3.12
Requires-Dist: boto3
Requires-Dist: click
Requires-Dist: pyperclip
Requires-Dist: rich
Requires-Dist: prompt-toolkit
Requires-Dist: setuptools>=40.8.0
